Challenge/001-Encoder/encoder8-3.v
`timescale 1ns/1ns

module encoder8_3(
    input a, b, c, d, e, f, g, h,
    output wire[2:0] s
);

    or s0 (s[0], b, d, f, h);
    or s1 (s[1], c, d, g, h);
    or s2 (s[2], e, f, g, h);

endmodule

STANDALONE-EXERCISES/Challenge/001-Encoder/encoder8-3_tb.v
`timescale 1ns/1ns

module encoder8_3_tb;

    reg a, b, c, d, e, f, g, h;
    wire [2:0] s;

    encoder8_3 dut01 (
        .a(a),
        .b(b),
        .c(c),
        .d(d),
        .e(e),
        .f(f),
        .h(h),
        .g(g),
        .s(s)
    );

    initial begin
        $dumpfile("encoder8_3.vcd");
        $dumpvars(0, encoder8_3_tb);
        $monitor("Tempo=%0td ns | Entradas (abcdefgh)=%b%b%b%b%b%b%b%b | Saída (s)=%b", 
                 $time, a, b, c, d, e, f, g, h, s);

        // Inicializa todas as entradas zeradas
        {a, b, c, d, e, f, g, h} = 8'b00000000;
        #10;

        // Teste 1: Apenas 'a' ativo
        {a, b, c, d, e, f, g, h} = 8'b10000000; #10;

        // Teste 2: Apenas 'b' ativo
        {a, b, c, d, e, f, g, h} = 8'b01000000; #10;

        // Teste 3: Apenas 'c' ativo
        {a, b, c, d, e, f, g, h} = 8'b00100000; #10;

        // Teste 4: Apenas 'd' ativo
        {a, b, c, d, e, f, g, h} = 8'b00010000; #10;

        // Teste 5: Apenas 'e' ativo
        {a, b, c, d, e, f, g, h} = 8'b00001000; #10;

        // Teste 6: Apenas 'f' ativo
        {a, b, c, d, e, f, g, h} = 8'b00000100; #10;

        // Teste 7: Apenas 'g' ativo
        {a, b, c, d, e, f, g, h} = 8'b00000010; #10;

        // Teste 8: Apenas 'h' ativo
        {a, b, c, d, e, f, g, h} = 8'b00000001; #10;
    end;


endmodule;

Challenge/001-Encoder/encoder8_3.vcd
$date
	Thu Aug 27 21:02:31 2026
$end
$version
	Icarus Verilog
$end
$timescale
	1ns
$end
$scope module encoder8_3_tb $end
$var wire 3 ! s [2:0] $end
$var reg 1 " a $end
$var reg 1 # b $end
$var reg 1 $ c $end
$var reg 1 % d $end
$var reg 1 & e $end
$var reg 1 ' f $end
$var reg 1 ( g $end
$var reg 1 ) h $end
$scope module dut01 $end
$var wire 1 " a $end
$var wire 1 # b $end
$var wire 1 $ c $end
$var wire 1 % d $end
$var wire 1 & e $end
$var wire 1 ' f $end
$var wire 1 ( g $end
$var wire 1 ) h $end
$var wire 3 * s [2:0] $end
$upscope $end
$upscope $end
$enddefinitions $end
$comment Show the parameter values. $end
$dumpall
$end
#0
$dumpvars
b0 *
0)
0(
0'
0&
0%
0$
0#
0"
b0 !
$end
#10
1"
#20
b1 !
b1 *
0"
1#
#30
b10 !
b10 *
0#
1$
#40
b11 !
b11 *
0$
1%
#50
b100 !
b100 *
0%
1&
#60
b101 !
b101 *
0&
1'
#70
b110 !
b110 *
0'
1(
#80
b111 !
b111 *
0(
1)
