HW/control.v
`timescale 1ns/1ns

module control(
    input clk, rst, start,
    input wire [1:0] count,
    output reg regclr, clken, done,
    output wire [2:0] state_out,
    output reg [1:0] in_sel, shift
);

    parameter [2:0] IDL = 3'b000,
                    LSB = 3'b001,
                    MID = 3'b010,
                    MSB = 3'b011,
                    ERR = 3'b100;

    reg [2:0] current_state, next_state;

    //Logica do Reset Assincrono e Registrador de Estado
    always @ (posedge clk or posedge rst) begin
        if (rst) current_state <= IDL;
        else current_state <= next_state;
    end

    //Logica do proximo estado
    always @ (*) begin 
        //Boa pratica para evitar latches: inicializar as saidas
        in_sel = 2'b00;
        shift = 2'b00;
        done = 1'b0;
        clken = 1'b0;
        regclr = 1'b0;
        next_state = current_state;

        case(current_state)
            IDL: begin
                if (start == 1'b1) begin 
                    next_state = LSB;
                    done = 1'b0;
                    clken = 1'b1;
                    regclr = 1'b0;
                end
                else begin 
                    next_state = IDL;
                    done = 1'b0;
                    clken = 1'b1;
                    regclr = 1'b1;
                end
            end
            LSB: begin
                if (start == 1'b0 && count == 2'b00) begin
                    next_state = MID;
                    in_sel = 2'b00;
                    shift = 2'b00;
                    done = 1'b0;
                    clken = 1'b0;
                    regclr = 1'b1;
                end
                else begin
                    next_state = ERR;
                    done = 1'b0;
                    clken = 1'b1;
                    regclr = 1'b1;
                end
            end
            MID: begin
                if (start == 1'b0 && count == 2'b01) begin
                    next_state = MID;
                    in_sel = 2'b01;
                    shift = 2'b01;
                    done = 1'b0;
                    clken = 1'b0;
                    regclr = 1'b1;
                end
                else if (start == 1'b0 && count == 2'b10) begin
                    next_state = MSB;
                    in_sel = 2'b10;
                    shift = 2'b01;
                    done = 1'b0;
                    clken = 1'b0;
                    regclr = 1'b1;
                end
                else begin
                    next_state = ERR;
                    done = 1'b0;
                    clken = 1'b1;
                    regclr = 1'b1;
                end
            end
            MSB: begin
                if (start == 1'b0 && count == 2'b11) begin 
                    next_state = IDL;
                    in_sel = 2'b11;
                    shift = 2'b10;
                    done = 1'b1;
                    clken = 1'b0;
                    regclr = 1'b1;
                end
                else begin
                    next_state = ERR;
                    done = 1'b0;
                    clken = 1'b1;
                    regclr = 1'b1;
                end
            end
            ERR: begin
                if (start == 1'b1) begin 
                    next_state = LSB;
                    done = 1'b0;
                    clken = 1'b1;
                    regclr = 1'b0;
                end
                else begin
                    next_state = ERR;
                    done = 1'b0;
                    clken = 1'b1;
                    regclr = 1'b1;
                end
            end
            default: next_state = IDL;
        endcase
    end

    assign state_out = current_state;

endmodule

SIMULATION/control_tb.v
`timescale 1ns/1ns

module control_tb;
    reg clk, rst, start;
    reg [1:0] count;
    wire regclr, clken, done;
    wire [2:0] state_out;
    wire [1:0] in_sel, shift;

    control DUT01(
        .clk(clk), .rst(rst), .start(start),
        .count(count),
        .regclr(regclr), .clken(clken), .done(done),
        .state_out(state_out),
        .in_sel(in_sel), .shift(shift)
    );

    initial clk = 1'b0;

    always #5 clk = ~clk;

    initial begin
        $dumpfile("SIMULATION/control.vcd");
        $dumpvars(0, control_tb);
        $display("TIME: %0t - INPUTS - clk: %b | rst: %b | start: %b | count: %b \n OUTPUTS - regclr: %b | clken: %b | done: %b | state_out: %b | in_sel: %b | shift: %b", $time, clk, rst, start, count, regclr, clken, done, state_out, in_sel, shift);
        $monitor("TIME: %0t - INPUTS - clk: %b | rst: %b | start: %b | count: %b \n OUTPUTS - regclr: %b | clken: %b | done: %b | state_out: %b | in_sel: %b | shift: %b", $time, clk, rst, start, count, regclr, clken, done, state_out, in_sel, shift);

        
        rst = 1'b0;
        start = 1'b0;
        count = 2'b00;

        //Agora tenho que pensar nos vetores de teste
        #7;
        rst = 1'b1;
        #1;
        rst = 1'b0;
        #4;
        start = 1'b1;
        #8;
        start = 1'b0;
        #7;
        count = 2'b01;
        #10;
        count = 2'b10;
        #10;
        count = 2'b11;
        #20;
        $finish;
    end



endmodule

SIMULATION/control.vcd
$date
	Tue Sep 22 20:49:57 2026
$end
$version
	Icarus Verilog
$end
$timescale
	1ns
$end
$scope module control_tb $end
$var wire 3 ! state_out [2:0] $end
$var wire 2 " shift [1:0] $end
$var wire 1 # regclr $end
$var wire 2 $ in_sel [1:0] $end
$var wire 1 % done $end
$var wire 1 & clken $end
$var reg 1 ' clk $end
$var reg 2 ( count [1:0] $end
$var reg 1 ) rst $end
$var reg 1 * start $end
$scope module DUT01 $end
$var wire 1 ' clk $end
$var wire 2 + count [1:0] $end
$var wire 1 ) rst $end
$var wire 1 * start $end
$var wire 3 , state_out [2:0] $end
$var parameter 3 - ERR $end
$var parameter 3 . IDL $end
$var parameter 3 / LSB $end
$var parameter 3 0 MID $end
$var parameter 3 1 MSB $end
$var reg 1 & clken $end
$var reg 3 2 current_state [2:0] $end
$var reg 1 % done $end
$var reg 2 3 in_sel [1:0] $end
$var reg 3 4 next_state [2:0] $end
$var reg 1 # regclr $end
$var reg 2 5 shift [1:0] $end
$upscope $end
$upscope $end
$enddefinitions $end
$comment Show the parameter values. $end
$dumpall
b11 1
b10 0
b1 /
b0 .
b100 -
$end
#0
$dumpvars
b0 5
b0 4
b0 3
bx 2
bx ,
b0 +
0*
0)
b0 (
0'
0&
0%
b0 $
0#
b0 "
bx !
$end
#5
1#
1&
b0 !
b0 ,
b0 2
1'
#7
1)
#8
0)
#10
0'
#12
b1 4
0#
1&
1*
#15
1#
b100 4
1&
b1 !
b1 ,
b1 2
1'
#20
b10 4
1#
0&
0'
0*
#25
1&
b100 4
1#
b10 !
b10 ,
b10 2
1'
#27
b1 "
b1 5
b1 $
b1 3
b10 4
1#
0&
b1 (
b1 +
#30
0'
#35
1'
#37
b11 4
1#
b1 "
b1 5
b10 $
b10 3
b10 (
b10 +
#40
0'
#45
1&
b100 4
1#
b0 "
b0 5
b0 $
b0 3
b11 !
b11 ,
b11 2
1'
#47
1%
b10 "
b10 5
b11 $
b11 3
b0 4
1#
0&
b11 (
b11 +
#50
0'
#55
1&
1#
0%
b0 "
b0 5
b0 $
b0 3
b0 !
b0 ,
b0 2
1'
