STANDALONE-EXERCISES/Exercise3/7seg_display.v
`timescale 1ns/1ns

module sevenseg_display(
    input wire [2:0] inp,
    output reg a, b, c, d, e, f, g
);

    always @ (*) begin
        case(inp)
            3'b000: begin
                a <= 1'b1; 
                b <= 1'b1;
                c <= 1'b1;
                d <= 1'b1;
                e <= 1'b1;
                f <= 1'b1;
                g <= 1'b0;  
            end
            3'b001: begin
                a <= 1'b0;
                b <= 1'b1;
                c <= 1'b1;
                d <= 1'b0;
                e <= 1'b0;
                f <= 1'b0;
                g <= 1'b0;
            end
            3'b010: begin
                a <= 1'b1;
                b <= 1'b1;
                c <= 1'b0;
                d <= 1'b1;
                e <= 1'b1;
                f <= 1'b0;
                g <= 1'b1;
            end
            3'b011: begin
                a <= 1'b1;
                b <= 1'b1;
                c <= 1'b1;
                d <= 1'b1;
                e <= 1'b0;
                f <= 1'b0;
                g <= 1'b1;
            end
            3'b100: begin
                a <= 1'b1;
                b <= 1'b0;
                c <= 1'b0;
                d <= 1'b1;
                e <= 1'b1;
                f <= 1'b1;
                g <= 1'b1;
            end
            3'b101: begin
                a <= 1'b1;
                b <= 1'b0;
                c <= 1'b0;
                d <= 1'b1;
                e <= 1'b1;
                f <= 1'b1;
                g <= 1'b1;
            end
            3'b110: begin
                a <= 1'b1;
                b <= 1'b0;
                c <= 1'b0;
                d <= 1'b1;
                e <= 1'b1;
                f <= 1'b1;
                g <= 1'b1;
            end
            3'b111: begin
                a <= 1'b1;
                b <= 1'b0;
                c <= 1'b0;
                d <= 1'b1;
                e <= 1'b1;
                f <= 1'b1;
                g <= 1'b1;
            end
        endcase
    end


endmodule;

SIMULATION/7seg_display_tb.v
`timescale 1ns/1ns

module sevenseg_display_tb;

    reg [2:0] inp;
    wire a, b, c, d, e, f, g;

    sevenseg_display DUT01(
        .inp(inp),
        .a(a),
        .b(b),
        .c(c),
        .d(d),
        .e(e),
        .f(f),
        .g(g)
    );

    initial begin
        $dumpfile("sevenseg_display.vcd");
        $dumpvars(0, sevenseg_display_tb);
        $monitor("Tempo=%0td ns | Entradas (inp)=%b | (abcdefg)=%b%b%b%b%b%b%b", 
                 $time, inp, a, b, c, d, e, f, g);
        inp = 3'b000; // Representa o caractere: '0'
        #40;
        inp = 3'b001; // Representa o caractere: '1'
        #40;
        inp = 3'b010; // Representa o caractere: '2'
        #40;
        inp = 3'b011; // Representa o caractere: '3'
        #40;
        inp = 3'b100; // Representa o caractere: 'E'
        #40;
        inp = 3'b101; // Representa o caractere: 'E'
        #40;
        inp = 3'b110; // Representa o caractere: 'E'
        #40;
        inp = 3'b111; // Representa o caractere: 'E'
    end


endmodule

STANDALONE-EXERCISES/Exercise3/sevenseg_display.vcd
$date
	Tue Sep  1 20:28:28 2026
$end
$version
	Icarus Verilog
$end
$timescale
	1ns
$end
$scope module sevenseg_display_tb $end
$var wire 1 ! g $end
$var wire 1 " f $end
$var wire 1 # e $end
$var wire 1 $ d $end
$var wire 1 % c $end
$var wire 1 & b $end
$var wire 1 ' a $end
$var reg 3 ( inp [2:0] $end
$scope module DUT01 $end
$var wire 3 ) inp [2:0] $end
$var reg 1 ' a $end
$var reg 1 & b $end
$var reg 1 % c $end
$var reg 1 $ d $end
$var reg 1 # e $end
$var reg 1 " f $end
$var reg 1 ! g $end
$upscope $end
$upscope $end
$enddefinitions $end
$comment Show the parameter values. $end
$dumpall
$end
#0
$dumpvars
b0 )
b0 (
1'
1&
1%
1$
1#
1"
0!
$end
#40
0"
0#
0$
0'
b1 (
b1 )
#80
1!
1#
1$
0%
1'
b10 (
b10 )
#120
0#
1%
b11 (
b11 )
#160
1"
1#
0%
0&
b100 (
b100 )
#200
b101 (
b101 )
#240
b110 (
b110 )
#280
b111 (
b111 )
