STANDALONE-EXERCISES/Exercise1/mult4x4.v
`timescale 1ns/1ns

module mult4x4(
    input wire [3:0] a, b,
    output wire [7:0] product
);

assign product = a * b;

endmodule

STANDALONE-EXERCISES/Exercise1/mult4x4_tb.v
`timescale 1ns/1ns

module mult4x4_tb;

reg [3:0] a, b;
wire [7:0] product;

    mult4x4 dut01(
        a,
        b,
        product
    );

    initial begin
        $dumpfile("mult4x4.vcd");
        $dumpvars(0, mult4x4_tb);

        $display("========================================");
        $display("        Multiplier 4x4 TESTBENCH");
        $display("========================================");
        $monitor("Time (ns): %0t | a=%0h b=%0h product=%0h",
        $time, a, b, product);

        a = 4'h0;
        b = 4'h2;
        #10;
        a = 4'h2;
        b = 4'h2;
        #10;
        a = 4'h4;
        b = 4'h2;
        #10;
        a = 4'h6;
        b = 4'h2;
        #10;
        a = 4'h7;
        b = 4'h2;
        #10;
        a = 4'h8;
        b = 4'h2;
        #10;
        a = 4'h9;
        b = 4'h2;
        #10;
        a = 4'hA;
        b = 4'h2;
        #10;
    end

endmodule

STANDALONE-EXERCISES/Exercise1/mult4x4.vcd
$date
	Tue Aug 25 20:52:09 2026
$end
$version
	Icarus Verilog
$end
$timescale
	1ns
$end
$scope module mult4x4_tb $end
$var wire 8 ! product [7:0] $end
$var reg 4 " a [3:0] $end
$var reg 4 # b [3:0] $end
$scope module dut01 $end
$var wire 4 $ a [3:0] $end
$var wire 4 % b [3:0] $end
$var wire 8 & product [7:0] $end
$upscope $end
$upscope $end
$enddefinitions $end
$comment Show the parameter values. $end
$dumpall
$end
#0
$dumpvars
b0 &
b10 %
b0 $
b10 #
b0 "
b0 !
$end
#10
b100 !
b100 &
b10 "
b10 $
#20
b1000 !
b1000 &
b100 "
b100 $
#30
b1100 !
b1100 &
b110 "
b110 $
#40
b1110 !
b1110 &
b111 "
b111 $
#50
b10000 !
b10000 &
b1000 "
b1000 $
#60
b10010 !
b10010 &
b1001 "
b1001 $
#70
b10100 !
b10100 &
b1010 "
b1010 $
